file_folder_tools/LICENSE
file_folder_tools/README.MD
file_folder_tools/__init__.py
file_folder_tools/requirements.txt
file_folder_tools/thirdparty.json
file_folder_tools-0.10.dist-info/LICENSE.rst
file_folder_tools-0.10.dist-info/METADATA
file_folder_tools-0.10.dist-info/WHEEL
file_folder_tools-0.10.dist-info/top_level.txt
file_folder_tools-0.10.dist-info/RECORD
