Metadata-Version: 2.1
Name: file-folder-tools
Version: 0.10
Summary: Some useful functions for files/folders
Home-page: https://github.com/hansalemaos/file_folder_tools
Author: Johannes Fischer
Author-email: <aulasparticularesdealemaosp@gmail.com>
License: MIT
Keywords: files,folders
Classifier: Development Status :: 4 - Beta
Classifier: Programming Language :: Python :: 3 :: Only
Classifier: Programming Language :: Python :: 3.9
Classifier: Topic :: Scientific/Engineering :: Visualization
Classifier: Topic :: Software Development :: Libraries :: Python Modules
Classifier: Topic :: Text Editors :: Text Processing
Classifier: Topic :: Text Processing :: General
Classifier: Topic :: Text Processing :: Indexing
Classifier: Topic :: Text Processing :: Filters
Classifier: Topic :: Utilities
License-File: LICENSE.rst
Requires-Dist: cryptography
Requires-Dist: flexible-partial
Requires-Dist: list-all-files-recursively
Requires-Dist: touchtouch
Requires-Dist: xxhash
